MANIFEST.in
README.txt
setup.cfg
setup.py
atreal/__init__.py
atreal.richfile.image.egg-info/PKG-INFO
atreal.richfile.image.egg-info/SOURCES.txt
atreal.richfile.image.egg-info/dependency_links.txt
atreal.richfile.image.egg-info/entry_points.txt
atreal.richfile.image.egg-info/namespace_packages.txt
atreal.richfile.image.egg-info/not-zip-safe
atreal.richfile.image.egg-info/requires.txt
atreal.richfile.image.egg-info/top_level.txt
atreal/richfile/__init__.py
atreal/richfile/image/__init__.py
atreal/richfile/image/adapters.py
atreal/richfile/image/configure.zcml
atreal/richfile/image/events.py
atreal/richfile/image/interfaces.py
atreal/richfile/image/browser/__init__.py
atreal/richfile/image/browser/configure.zcml
atreal/richfile/image/browser/controlpanel.pt
atreal/richfile/image/browser/controlpanel.py
atreal/richfile/image/browser/image.kss
atreal/richfile/image/browser/richfileimage_icon.png
atreal/richfile/image/browser/view.pt
atreal/richfile/image/browser/viewlet.pt
atreal/richfile/image/browser/viewlets.py
atreal/richfile/image/browser/views.py
atreal/richfile/image/locales/atreal.richfile.image.pot
atreal/richfile/image/locales/fr/LC_MESSAGES/atreal.richfile.image.po
atreal/richfile/image/profiles/default/actionicons.xml
atreal/richfile/image/profiles/default/browserlayer.xml
atreal/richfile/image/profiles/default/componentregistry.xml
atreal/richfile/image/profiles/default/controlpanel.xml
atreal/richfile/image/profiles/default/kssregistry.xml
atreal/richfile/image/profiles/default/metadata.xml