Metadata-Version: 1.0
Name: atreal.richfile.image
Version: 1.0.0rc1
Summary: Image Support Plugin for RichFileQualifier
Home-page: http://www.atreal.net/
Author: atReal
Author-email: contact@atreal.net
License: GPL
Keywords: plone richfile atreal image
Platform: UNKNOWN
Classifier: Framework :: Plone
Classifier: Programming Language :: Python
Classifier: Topic :: Software Development :: Libraries :: Python Modules
